gitcomp/__init__.py
gitcomp/__main__.py
gitcomp/gitcomp_core.py
gitcomp/net_mod.py
gitcomp/repository.py
gitcomp/ser_de.py
gitcomp/user.py
gitcomp-1.0.4.dist-info/LICENSE
gitcomp-1.0.4.dist-info/METADATA
gitcomp-1.0.4.dist-info/WHEEL
gitcomp-1.0.4.dist-info/entry_points.txt
gitcomp-1.0.4.dist-info/top_level.txt
gitcomp-1.0.4.dist-info/RECORD
