Metadata-Version: 2.1
Name: gitcomp
Version: 1.0.4
Summary: A python based command line tool to compare Github Users or Repositories.
Home-page: https://github.com/avaish1409/gitcomp
Author: Anirudh Vaish
Author-email: anirudhvaish147@gmail.com
License: MIT
Project-URL: Bug Tracker, https://github.com/avaish1409/gitcomp/issues
Project-URL: Documentation, https://avaish1409.github.io/gitcomp/
Project-URL: Source, https://github.com/avaish1409/gitcomp
Keywords: command-line-tools cli gitcomp python package compare git github
Platform: UNKNOWN
Classifier: Programming Language :: Python :: 3
Classifier: License :: OSI Approved :: MIT License
Classifier: Operating System :: OS Independent
Requires-Python: >=3.6
License-File: LICENSE
Requires-Dist: tabulate (==0.8.9)
Requires-Dist: urllib3 (==1.25.8)
Requires-Dist: wcwidth (==0.1.8)
